mathnum.py
mathnum-0.1.0.dist-info/METADATA
mathnum-0.1.0.dist-info/WHEEL
mathnum-0.1.0.dist-info/RECORD
